{
  "meta": {
    "url": "https://www.bundestag.de/parlament/plenum/abstimmung/abstimmung?id=138"
  },
  "data": {
    "id": "138",
    "date": "2012-11-22T00:00:00.000Z",
    "title": "Änderungsantrag zum Haushalt 2013 (Familie)",
    "topTitle": "",
    "description": "Änderungsantrag der SPD zum Bundeshaushaltsplans 2013: Einzelplan 17 Bundesministeriums für Familie, Senioren, Frauen und Jugend (Drucksachen <a target='_blank' href=\"http://dip21.bundestag.de/dip21/btd/17/102/1710200.pdf\" class=\"dipLink\" title=\"Die PDF-Datei Drucksache 17/10200 öffnet sich in einem neuen Fenster\"><i class=\"icon-doc\"></i>17/10200</a>, <a target='_blank' href=\"http://dip21.bundestag.de/dip21/btd/17/102/1710202.pdf\" class=\"dipLink\" title=\"Die PDF-Datei Drucksache 17/10202 öffnet sich in einem neuen Fenster\"><i class=\"icon-doc\"></i>17/10202</a>, <a target='_blank' href=\"http://dip21.bundestag.de/dip21/btd/17/108/1710816.pdf\" class=\"dipLink\" title=\"Die PDF-Datei Drucksache 17/10816 öffnet sich in einem neuen Fenster\"><i class=\"icon-doc\"></i>17/10816</a>, <a target='_blank' href=\"http://dip21.bundestag.de/dip21/btd/17/108/1710823.pdf\" class=\"dipLink\" title=\"Die PDF-Datei Drucksache 17/10823 öffnet sich in einem neuen Fenster\"><i class=\"icon-doc\"></i>17/10823</a>, <a target='_blank' href=\"http://dip21.bundestag.de/dip21/btd/17/108/1710824.pdf\" class=\"dipLink\" title=\"Die PDF-Datei Drucksache 17/10824 öffnet sich in einem neuen Fenster\"><i class=\"icon-doc\"></i>17/10824</a>, <a target='_blank' href=\"http://dip21.bundestag.de/dip21/btd/17/108/1710825.pdf\" class=\"dipLink\" title=\"Die PDF-Datei Drucksache 17/10825 öffnet sich in einem neuen Fenster\"><i class=\"icon-doc\"></i>17/10825</a> und <a target='_blank' href=\"http://dip21.bundestag.de/dip21/btd/17/115/1711548.pdf\" class=\"dipLink\" title=\"Die PDF-Datei Drucksache 17/11548 öffnet sich in einem neuen Fenster\"><i class=\"icon-doc\"></i>17/11548</a>)",
    "detailedDescription": "",
    "documents": [
      "http://dip21.bundestag.de/dip21/btd/17/102/1710200.pdf",
      "http://dip21.bundestag.de/dip21/btd/17/102/1710202.pdf",
      "http://dip21.bundestag.de/dip21/btd/17/108/1710816.pdf",
      "http://dip21.bundestag.de/dip21/btd/17/108/1710823.pdf",
      "http://dip21.bundestag.de/dip21/btd/17/108/1710824.pdf",
      "http://dip21.bundestag.de/dip21/btd/17/108/1710825.pdf",
      "http://dip21.bundestag.de/dip21/btd/17/115/1711548.pdf"
    ],
    "deputyVotesURL": "https://www.bundestag.de/apps/na/na/namensliste.form?id=138&ajax=true",
    "votes": {
      "all": {
        "total": 620,
        "yes": 261,
        "no": 306,
        "abstain": 0,
        "na": 53
      },
      "parties": [
        {
          "name": "CDU/CSU",
          "votes": {
            "total": 237,
            "yes": 0,
            "no": 221,
            "abstain": 0,
            "na": 16
          }
        },
        {
          "name": "SPD",
          "votes": {
            "total": 146,
            "yes": 135,
            "no": 0,
            "abstain": 0,
            "na": 11
          }
        },
        {
          "name": "FDP",
          "votes": {
            "total": 93,
            "yes": 0,
            "no": 85,
            "abstain": 0,
            "na": 8
          }
        },
        {
          "name": "DIE LINKE.",
          "votes": {
            "total": 76,
            "yes": 66,
            "no": 0,
            "abstain": 0,
            "na": 10
          }
        },
        {
          "name": "B90/GRÜNE",
          "votes": {
            "total": 68,
            "yes": 60,
            "no": 0,
            "abstain": 0,
            "na": 8
          }
        }
      ]
    },
    "plenarProtocolURL": "",
    "media": {
      "iTunesURL": "",
      "mediathekURL": "",
      "videoURLs": []
    },
    "speeches": []
  }
}