{
  "meta": {
    "url": "https://www.bundestag.de/parlament/plenum/abstimmung/abstimmung?id=21"
  },
  "data": {
    "id": "21",
    "date": "2011-03-25T00:00:00.000Z",
    "title": "Mandatsverlängerung in Afghanistan (ISAF)",
    "topTitle": "",
    "description": "Beschlussempfehlung des Auswärtigen Ausschusses (Drucksache <a target='_blank' href=\"http://dip21.bundestag.de/dip21/btd/17/052/1705251.pdf\" class=\"dipLink\" title=\"Die PDF-Datei Drucksache 17/5251 öffnet sich in einem neuen Fenster\"><i class=\"icon-doc\"></i>17/5251</a>) angenommen, das bedeutet: Antrag der Bundesregierung (Drucksache <a target='_blank' href=\"http://dip21.bundestag.de/dip21/btd/17/051/1705190.pdf\" class=\"dipLink\" title=\"Die PDF-Datei Drucksache 17/5190 öffnet sich in einem neuen Fenster\"><i class=\"icon-doc\"></i>17/5190</a>) angenommen",
    "detailedDescription": "",
    "documents": [
      "http://dip21.bundestag.de/dip21/btd/17/052/1705251.pdf",
      "http://dip21.bundestag.de/dip21/btd/17/051/1705190.pdf"
    ],
    "deputyVotesURL": "https://www.bundestag.de/apps/na/na/namensliste.form?id=21&ajax=true",
    "votes": {
      "all": {
        "total": 621,
        "yes": 407,
        "no": 113,
        "abstain": 33,
        "na": 68
      },
      "parties": [
        {
          "name": "CDU/CSU",
          "votes": {
            "total": 238,
            "yes": 217,
            "no": 2,
            "abstain": 1,
            "na": 18
          }
        },
        {
          "name": "SPD",
          "votes": {
            "total": 146,
            "yes": 93,
            "no": 26,
            "abstain": 6,
            "na": 21
          }
        },
        {
          "name": "FDP",
          "votes": {
            "total": 93,
            "yes": 82,
            "no": 0,
            "abstain": 2,
            "na": 9
          }
        },
        {
          "name": "DIE LINKE.",
          "votes": {
            "total": 76,
            "yes": 0,
            "no": 64,
            "abstain": 0,
            "na": 12
          }
        },
        {
          "name": "B90/GRÜNE",
          "votes": {
            "total": 68,
            "yes": 15,
            "no": 21,
            "abstain": 24,
            "na": 8
          }
        }
      ]
    },
    "plenarProtocolURL": "",
    "media": {
      "iTunesURL": "",
      "mediathekURL": "",
      "videoURLs": []
    },
    "speeches": []
  }
}