{
  "meta": {
    "url": "https://www.bundestag.de/parlament/plenum/abstimmung/abstimmung?id=24"
  },
  "data": {
    "id": "24",
    "date": "2012-05-25T00:00:00.000Z",
    "title": "Mandatsverlängerung im Kosovo",
    "topTitle": "182. Sitzung vom 25.05.2012, TOP 5 KFOR-Einsatz",
    "description": "Beschlussempfehlung des Auswärtigen Ausschusses (Drucksache <a target='_blank' href=\"http://dip21.bundestag.de/dip21/btd/17/097/1709768.pdf\" class=\"dipLink\" title=\"Die PDF-Datei Drucksache 17/9768 öffnet sich in einem neuen Fenster\"><i class=\"icon-doc\"></i>17/9768</a>)angenommen, das bedeutet: Antrag der Bundesregierung (Drucksache <a target='_blank' href=\"http://dip21.bundestag.de/dip21/btd/17/095/1709505.pdf\" class=\"dipLink\" title=\"Die PDF-Datei Drucksache 17/9505 öffnet sich in einem neuen Fenster\"><i class=\"icon-doc\"></i>17/9505</a>) angenommen",
    "detailedDescription": "5.) Beratung BeschlEmpf u Ber (3.A)\r<br/>zum Antrag BReg\r<br/>Fortsetzung der deutschen Beteiligung an der internationalen Sicherheitspräsenz in Kosovo auf der Grundlage der Resolution 1244 (1999) des Sicherheitsrates der Vereinten Nationen vom 10.6.1999 und des Militärisch-Technischen Abkommens zwischen der internationalen Sicherheitspräsenz (KFOR) und den Regierungen der Bundesrepublik Jugoslawien (jetzt: Republik Serbien) und der Republik Serbien\r<br/>vom 9.6.1999\r<br/>- Drs <a target='_blank' href=\"http://dip21.bundestag.de/dip21/btd/17/095/1709505.pdf\" class=\"dipLink\" title=\"Die PDF-Datei Drucksache 17/9505 öffnet sich in einem neuen Fenster\"><i class=\"icon-doc\"></i>17/9505</a>, <a target='_blank' href=\"http://dip21.bundestag.de/dip21/btd/17/097/1709768.pdf\" class=\"dipLink\" title=\"Die PDF-Datei Drucksache 17/9768 öffnet sich in einem neuen Fenster\"><i class=\"icon-doc\"></i>17/9768</a>, <a target='_blank' href=\"http://dip21.bundestag.de/dip21/btd/17/097/1709772.pdf\" class=\"dipLink\" title=\"Die PDF-Datei Drucksache 17/9772 öffnet sich in einem neuen Fenster\"><i class=\"icon-doc\"></i>17/9772</a> -",
    "documents": [
      "http://dip21.bundestag.de/dip21/btd/17/097/1709768.pdf",
      "http://dip21.bundestag.de/dip21/btd/17/095/1709505.pdf"
    ],
    "deputyVotesURL": "https://www.bundestag.de/apps/na/na/namensliste.form?id=24&ajax=true",
    "votes": {
      "all": {
        "total": 620,
        "yes": 486,
        "no": 70,
        "abstain": 8,
        "na": 56
      },
      "parties": [
        {
          "name": "CDU/CSU",
          "votes": {
            "total": 237,
            "yes": 222,
            "no": 1,
            "abstain": 0,
            "na": 14
          }
        },
        {
          "name": "SPD",
          "votes": {
            "total": 146,
            "yes": 120,
            "no": 0,
            "abstain": 3,
            "na": 23
          }
        },
        {
          "name": "FDP",
          "votes": {
            "total": 93,
            "yes": 88,
            "no": 1,
            "abstain": 0,
            "na": 4
          }
        },
        {
          "name": "DIE LINKE.",
          "votes": {
            "total": 76,
            "yes": 0,
            "no": 67,
            "abstain": 0,
            "na": 9
          }
        },
        {
          "name": "B90/GRÜNE",
          "votes": {
            "total": 68,
            "yes": 56,
            "no": 1,
            "abstain": 5,
            "na": 6
          }
        }
      ]
    },
    "plenarProtocolURL": "https://dipbt.bundestag.de/dip21/btp/17/17182.pdf#P.21675",
    "media": {
      "iTunesURL": "itpc://webtv.bundestag.de/player/macros/bttv/podcast/video/auswahl.xml?contentIds=1715896",
      "mediathekURL": "https://dbtg.tv/fvid/1715896",
      "videoURLs": [
        {
          "URL": "https://cldf-od.r53.cdn.tv1.eu/1000153copo/ondemand/app144277506/145293313/1715896/1715896_h264_720_400_2000kb_baseline_de_2192.mp4?fdl=1",
          "description": "hoch (5000 kb)"
        },
        {
          "URL": "https://cldf-od.r53.cdn.tv1.eu/1000153copo/ondemand/app144277506/145293313/1715896/1715896_h264_720_400_2000kb_baseline_de_2192.mp4?fdl=1",
          "description": "mittel (2000 kb)"
        },
        {
          "URL": "https://cldf-od.r53.cdn.tv1.eu/1000153copo/ondemand/app144277506/145293313/1715896/1715896_h264_512_288_514kb_baseline_de_514.mp4?fdl=1",
          "description": "niedrig (514 kb)"
        },
        {
          "URL": "https://cldf-od.r53.cdn.tv1.eu/1000153copo/ondemand/app144277506/145293313/1715896/1715896_mp3_128kb_stereo_de_128.mp3?fdl=1",
          "description": "Audio (MP3)"
        }
      ]
    },
    "speeches": [
      {
        "deputyName": "Göring-Eckardt, Katrin",
        "deputyImgURL": "https://www.bundestag.de/resource/image/519780/3x4/170/227/8caec0b17d0ec4852f2fee9c064ea3b3/LS/goering_eckardt_katrin_gross.jpg",
        "mediathekURL": "https://www.bundestag.de/mediathek?videoid=1715898#url=L21lZGlhdGhla292ZXJsYXk=&mod=mod536668",
        "function": null,
        "party": "Bündnis 90/Die Grünen"
      },
      {
        "deputyName": "Stinner, Dr. Rainer",
        "deputyImgURL": "https://www.bundestag.de/resource/image/451040/3x4/170/227/e4de578fad7a1bd7ded6b040ad6a94b1/xy/nn_bild_m.jpg",
        "mediathekURL": "https://www.bundestag.de/mediathek?videoid=1715899#url=L21lZGlhdGhla292ZXJsYXk=&mod=mod536668",
        "function": null,
        "party": "FDP"
      },
      {
        "deputyName": "Arnold, Rainer",
        "deputyImgURL": "https://www.bundestag.de/resource/image/240720/3x4/170/227/591732dde823711479c2956b4139698c/AO/arnold_rainer_gross.jpg",
        "mediathekURL": "https://www.bundestag.de/mediathek?videoid=1715901#url=L21lZGlhdGhla292ZXJsYXk=&mod=mod536668",
        "function": null,
        "party": "SPD"
      },
      {
        "deputyName": "Beyer, Peter",
        "deputyImgURL": "https://www.bundestag.de/resource/image/518392/3x4/170/227/61679a5fe467aed619d8432a42abec38/bY/beyer_peter_gross.jpg",
        "mediathekURL": "https://www.bundestag.de/mediathek?videoid=1715919#url=L21lZGlhdGhla292ZXJsYXk=&mod=mod536668",
        "function": null,
        "party": "CDU/CSU"
      },
      {
        "deputyName": "Höger, Inge",
        "deputyImgURL": "https://www.bundestag.de/resource/image/241096/3x4/170/227/f939b8fc56ec6ee77f8dab2a1954daa/wZ/hoeger_inge_gross.jpg",
        "mediathekURL": "https://www.bundestag.de/mediathek?videoid=1716524#url=L21lZGlhdGhla292ZXJsYXk=&mod=mod536668",
        "function": null,
        "party": "Die Linke"
      },
      {
        "deputyName": "Nouripour, Omid",
        "deputyImgURL": "https://www.bundestag.de/resource/image/522402/3x4/170/227/c8c8407c51d31f38d37ec16a1788f455/gO/nouripour_omid_gross.jpg",
        "mediathekURL": "https://www.bundestag.de/mediathek?videoid=1716525#url=L21lZGlhdGhla292ZXJsYXk=&mod=mod536668",
        "function": null,
        "party": "Bündnis 90/Die Grünen"
      },
      {
        "deputyName": "Hahn, Florian",
        "deputyImgURL": "https://www.bundestag.de/resource/image/520044/3x4/170/227/5c44c823156e6b3d5063768b84d5dfb9/Wm/hahn_florian_gross.jpg",
        "mediathekURL": "https://www.bundestag.de/mediathek?videoid=1716529#url=L21lZGlhdGhla292ZXJsYXk=&mod=mod536668",
        "function": null,
        "party": "CDU/CSU"
      },
      {
        "deputyName": "Göring-Eckardt, Katrin",
        "deputyImgURL": "https://www.bundestag.de/resource/image/519780/3x4/170/227/8caec0b17d0ec4852f2fee9c064ea3b3/LS/goering_eckardt_katrin_gross.jpg",
        "mediathekURL": "https://www.bundestag.de/mediathek?videoid=1716530#url=L21lZGlhdGhla292ZXJsYXk=&mod=mod536668",
        "function": null,
        "party": "Bündnis 90/Die Grünen"
      }
    ]
  }
}