{
  "meta": {
    "url": "https://www.bundestag.de/parlament/plenum/abstimmung/abstimmung?id=604"
  },
  "data": {
    "id": "604",
    "date": "2019-05-17T00:00:00.000Z",
    "title": "BDS-Bewegung verurteilen - Existenz des Staates Israel schützen",
    "topTitle": "102. Sitzung vom 17.05.2019, TOP ZP 11, 12, 14 BDS-Bewegung",
    "description": "Antrag der Abgeordneten Jürgen Braun, Beatrix von Storch, Dr. Anton Friesen, weiterer Abgeordneter und der Fraktion der AfD: BDS-Bewegung verurteilen - Existenz des Staates Israel schützen (Drucksache <a target='_blank' href=\"http://dip21.bundestag.de/dip21/btd/19/097/1909757.pdf\" class=\"dipLink\" title=\"Die PDF-Datei Drucksache 19/9757 öffnet sich in einem neuen Fenster\"><i class=\"icon-doc\"></i>19/9757</a>)",
    "detailedDescription": "ZP 11) Beratung des Antrags der Fraktionen CDU/CSU, SPD, FDP und BÜNDNIS 90/DIE GRÜNEN <br/>Der BDS-Bewegung entschlossen entgegentreten – Antisemitismus bekämpfen<br/>Drucksache <a target='_blank' href=\"http://dip21.bundestag.de/dip21/btd/19/101/1910191.pdf\" class=\"dipLink\" title=\"Die PDF-Datei Drucksache 19/10191 öffnet sich in einem neuen Fenster\"><i class=\"icon-doc\"></i>19/10191</a><br/><br/>ZP 12) Beratung des Antrags der Fraktion der AfD <br/>BDS-Bewegung verurteilen – Existenz des Staates Israel schützen<br/>Drucksache <a target='_blank' href=\"http://dip21.bundestag.de/dip21/btd/19/097/1909757.pdf\" class=\"dipLink\" title=\"Die PDF-Datei Drucksache 19/9757 öffnet sich in einem neuen Fenster\"><i class=\"icon-doc\"></i>19/9757</a><br/><br/>ZP 14) Beratung des Antrags der Fraktion DIE LINKE. <br/>BDS-Bewegung ablehnen – Friedliche Lösung im Nahen Osten befördern<br/>Drucksache <a target='_blank' href=\"http://dip21.bundestag.de/dip21/btd/19/102/1910261.pdf\" class=\"dipLink\" title=\"Die PDF-Datei Drucksache 19/10261 öffnet sich in einem neuen Fenster\"><i class=\"icon-doc\"></i>19/10261</a><br/><br/>Namentliche Abstimmung<br/>",
    "documents": [
      "http://dip21.bundestag.de/dip21/btd/19/097/1909757.pdf"
    ],
    "deputyVotesURL": "https://www.bundestag.de/apps/na/na/namensliste.form?id=604&ajax=true",
    "votes": {
      "all": {
        "total": 709,
        "yes": 62,
        "no": 431,
        "abstain": 2,
        "na": 214
      },
      "parties": [
        {
          "name": "CDU/CSU",
          "votes": {
            "total": 246,
            "yes": 0,
            "no": 184,
            "abstain": 0,
            "na": 62
          }
        },
        {
          "name": "SPD",
          "votes": {
            "total": 152,
            "yes": 1,
            "no": 106,
            "abstain": 0,
            "na": 45
          }
        },
        {
          "name": "AfD",
          "votes": {
            "total": 91,
            "yes": 61,
            "no": 0,
            "abstain": 1,
            "na": 29
          }
        },
        {
          "name": "FDP",
          "votes": {
            "total": 80,
            "yes": 0,
            "no": 54,
            "abstain": 0,
            "na": 26
          }
        },
        {
          "name": "DIE LINKE.",
          "votes": {
            "total": 69,
            "yes": 0,
            "no": 41,
            "abstain": 0,
            "na": 28
          }
        },
        {
          "name": "B90/GRÜNE",
          "votes": {
            "total": 67,
            "yes": 0,
            "no": 46,
            "abstain": 0,
            "na": 21
          }
        },
        {
          "name": "fraktionslose",
          "votes": {
            "total": 4,
            "yes": 0,
            "no": 0,
            "abstain": 1,
            "na": 3
          }
        }
      ]
    },
    "plenarProtocolURL": "http://dipbt.bundestag.de/dip21/btp/19/19102.pdf#P.12523",
    "media": {
      "iTunesURL": "itpc://webtv.bundestag.de/player/macros/bttv/podcast/video/auswahl.xml?contentIds=7356252",
      "mediathekURL": "https://dbtg.tv/fvid/7356252",
      "videoURLs": [
        {
          "URL": "https://cldf-od.r53.cdn.tv1.eu/1000153copo/ondemand/app144277506/145293313/7356252/7356252_h264_1920_1080_5000kb_baseline_de_5000.mp4?fdl=1",
          "description": "hoch (5000 kb)"
        },
        {
          "URL": "https://cldf-od.r53.cdn.tv1.eu/1000153copo/ondemand/app144277506/145293313/7356252/7356252_h264_720_400_2000kb_baseline_de_2192.mp4?fdl=1",
          "description": "mittel (2000 kb)"
        },
        {
          "URL": "https://cldf-od.r53.cdn.tv1.eu/1000153copo/ondemand/app144277506/145293313/7356252/7356252_h264_512_288_514kb_baseline_de_514.mp4?fdl=1",
          "description": "niedrig (514 kb)"
        },
        {
          "URL": "https://cldf-od.r53.cdn.tv1.eu/1000153copo/ondemand/app144277506/145293313/7356252/7356252_mp3_128kb_stereo_de_128.mp3?fdl=1",
          "description": "Audio (MP3)"
        }
      ]
    },
    "speeches": [
      {
        "deputyName": "Roth (Augsburg), Claudia",
        "deputyImgURL": "https://www.bundestag.de/resource/image/241488/3x4/170/227/83f507684155dbcebabdc45458bc5c2/bC/roth_claudia_gross.jpg",
        "mediathekURL": "https://www.bundestag.de/mediathek?videoid=7356255#url=L21lZGlhdGhla292ZXJsYXk=&mod=mod536668",
        "function": "Bundestagsvizepräsidentin",
        "party": null
      },
      {
        "deputyName": "Müller, Axel",
        "deputyImgURL": "https://www.bundestag.de/resource/image/451040/3x4/170/227/e4de578fad7a1bd7ded6b040ad6a94b1/xy/nn_bild_m.jpg",
        "mediathekURL": "https://www.bundestag.de/mediathek?videoid=7356256#url=L21lZGlhdGhla292ZXJsYXk=&mod=mod536668",
        "function": null,
        "party": "CDU/CSU"
      },
      {
        "deputyName": "Braun, Jürgen",
        "deputyImgURL": "https://www.bundestag.de/resource/image/451040/3x4/170/227/e4de578fad7a1bd7ded6b040ad6a94b1/xy/nn_bild_m.jpg",
        "mediathekURL": "https://www.bundestag.de/mediathek?videoid=7356257#url=L21lZGlhdGhla292ZXJsYXk=&mod=mod536668",
        "function": null,
        "party": "AfD"
      },
      {
        "deputyName": "Lange (Backnang), Christian",
        "deputyImgURL": "https://www.bundestag.de/resource/image/241278/3x4/170/227/979a3430aab63b7e034440b0e3b18de1/QX/lange_christian_gross.jpg",
        "mediathekURL": "https://www.bundestag.de/mediathek?videoid=7356259#url=L21lZGlhdGhla292ZXJsYXk=&mod=mod536668",
        "function": "Parlamentarischer Staatssekretär der Justiz und für Verbraucherschutz",
        "party": null
      },
      {
        "deputyName": "Djir-Sarai, Bijan",
        "deputyImgURL": "https://www.bundestag.de/resource/image/451040/3x4/170/227/e4de578fad7a1bd7ded6b040ad6a94b1/xy/nn_bild_m.jpg",
        "mediathekURL": "https://www.bundestag.de/mediathek?videoid=7356260#url=L21lZGlhdGhla292ZXJsYXk=&mod=mod536668",
        "function": null,
        "party": "FDP"
      },
      {
        "deputyName": "Hänsel, Heike",
        "deputyImgURL": "https://www.bundestag.de/resource/image/241068/3x4/170/227/7406458d6d10f279c60fea756a4ff7d/LB/haensel_heike_gross.jpg",
        "mediathekURL": "https://www.bundestag.de/mediathek?videoid=7356261#url=L21lZGlhdGhla292ZXJsYXk=&mod=mod536668",
        "function": null,
        "party": "Die Linke"
      },
      {
        "deputyName": "Nouripour, Omid",
        "deputyImgURL": "https://www.bundestag.de/resource/image/241412/3x4/170/227/92de0dca388dd876534991653bd7741d/za/nouripour_omid_gross.jpg",
        "mediathekURL": "https://www.bundestag.de/mediathek?videoid=7356264#url=L21lZGlhdGhla292ZXJsYXk=&mod=mod536668",
        "function": null,
        "party": "Bündnis 90/Die Grünen"
      },
      {
        "deputyName": "Mieruch, Mario",
        "deputyImgURL": "https://www.bundestag.de/resource/image/451040/3x4/170/227/e4de578fad7a1bd7ded6b040ad6a94b1/xy/nn_bild_m.jpg",
        "mediathekURL": "https://www.bundestag.de/mediathek?videoid=7356265#url=L21lZGlhdGhla292ZXJsYXk=&mod=mod536668",
        "function": null,
        "party": "fraktionslos "
      },
      {
        "deputyName": "Brehm, Sebastian",
        "deputyImgURL": "https://www.bundestag.de/resource/image/451040/3x4/170/227/e4de578fad7a1bd7ded6b040ad6a94b1/xy/nn_bild_m.jpg",
        "mediathekURL": "https://www.bundestag.de/mediathek?videoid=7356266#url=L21lZGlhdGhla292ZXJsYXk=&mod=mod536668",
        "function": null,
        "party": "CDU/CSU"
      },
      {
        "deputyName": "Lindh, Helge",
        "deputyImgURL": "https://www.bundestag.de/resource/image/451040/3x4/170/227/e4de578fad7a1bd7ded6b040ad6a94b1/xy/nn_bild_m.jpg",
        "mediathekURL": "https://www.bundestag.de/mediathek?videoid=7356267#url=L21lZGlhdGhla292ZXJsYXk=&mod=mod536668",
        "function": null,
        "party": "SPD"
      },
      {
        "deputyName": "Roth (Augsburg), Claudia",
        "deputyImgURL": "https://www.bundestag.de/resource/image/241488/3x4/170/227/83f507684155dbcebabdc45458bc5c2/bC/roth_claudia_gross.jpg",
        "mediathekURL": "https://www.bundestag.de/mediathek?videoid=7356270#url=L21lZGlhdGhla292ZXJsYXk=&mod=mod536668",
        "function": "Bundestagsvizepräsidentin",
        "party": null
      }
    ]
  }
}