{
  "meta": {
    "url": "https://www.bundestag.de/parlament/plenum/abstimmung/abstimmung?id=645"
  },
  "data": {
    "id": "645",
    "date": "2019-12-19T00:00:00.000Z",
    "title": "Föderale Sicherheitsarchitektur",
    "topTitle": "137. Sitzung vom 19.12.2019, TOP 9 Föderale Sicherheitsarchitektur",
    "description": "Beschlussempfehlung des Ausschusses für Inneres und Heimat (4. Ausschuss) zu dem Antrag der Abgeordneten Benjamin Strasser, Konstantin Kuhle, Stephan Thomae, weiterer Abgeordneter und der Fraktion der FDP: Terrorismus effektiv bekämpfen, Verantwortlichkeiten klären - Einsetzung einer Kommission zur Reform der föderalen Sicherheitsarchitektur (Drucksache <a target='_blank' href=\"https://dip21.bundestag.de/dip21/btd/19/074/1907424.pdf\" class=\"dipLink\" title=\"Die PDF-Datei Drucksache 19/7424 öffnet sich in einem neuen Fenster\"><i class=\"icon-doc\"></i>19/7424</a> und <a target='_blank' href=\"https://dip21.bundestag.de/dip21/btd/19/151/1915129.pdf\" class=\"dipLink\" title=\"Die PDF-Datei Drucksache 19/15129 öffnet sich in einem neuen Fenster\"><i class=\"icon-doc\"></i>19/15129</a>)",
    "detailedDescription": "Beratung der Beschlussempfehlung und des Berichts des Ausschusses für Inneres und Heimat (4. Ausschuss) <br/>zu dem Antrag der Fraktion der FDP<br/>Terrorismus effektiv bekämpfen, Verantwortlichkeiten klären – Einsetzung einer Kommission zur Reform der föderalen Sicherheitsarchitektur – Föderalismuskommission III<br/>Drucksachen <a target='_blank' href=\"https://dip21.bundestag.de/dip21/btd/19/074/1907424.pdf\" class=\"dipLink\" title=\"Die PDF-Datei Drucksache 19/7424 öffnet sich in einem neuen Fenster\"><i class=\"icon-doc\"></i>19/7424</a>, <a target='_blank' href=\"https://dip21.bundestag.de/dip21/btd/19/151/1915129.pdf\" class=\"dipLink\" title=\"Die PDF-Datei Drucksache 19/15129 öffnet sich in einem neuen Fenster\"><i class=\"icon-doc\"></i>19/15129</a><br/><br/>namentliche Abstimmung<br/>",
    "documents": [
      "https://dip21.bundestag.de/dip21/btd/19/074/1907424.pdf",
      "https://dip21.bundestag.de/dip21/btd/19/151/1915129.pdf"
    ],
    "deputyVotesURL": "https://www.bundestag.de/apps/na/na/namensliste.form?id=645&ajax=true",
    "votes": {
      "all": {
        "total": 709,
        "yes": 506,
        "no": 139,
        "abstain": 3,
        "na": 61
      },
      "parties": [
        {
          "name": "CDU/CSU",
          "votes": {
            "total": 246,
            "yes": 228,
            "no": 0,
            "abstain": 1,
            "na": 17
          }
        },
        {
          "name": "SPD",
          "votes": {
            "total": 152,
            "yes": 139,
            "no": 0,
            "abstain": 0,
            "na": 13
          }
        },
        {
          "name": "AfD",
          "votes": {
            "total": 90,
            "yes": 77,
            "no": 0,
            "abstain": 1,
            "na": 12
          }
        },
        {
          "name": "FDP",
          "votes": {
            "total": 80,
            "yes": 0,
            "no": 73,
            "abstain": 0,
            "na": 7
          }
        },
        {
          "name": "DIE LINKE.",
          "votes": {
            "total": 69,
            "yes": 60,
            "no": 0,
            "abstain": 0,
            "na": 9
          }
        },
        {
          "name": "B90/GRÜNE",
          "votes": {
            "total": 67,
            "yes": 0,
            "no": 65,
            "abstain": 0,
            "na": 2
          }
        },
        {
          "name": "fraktionslose",
          "votes": {
            "total": 5,
            "yes": 2,
            "no": 1,
            "abstain": 1,
            "na": 1
          }
        }
      ]
    },
    "plenarProtocolURL": "https://dipbt.bundestag.de/dip21/btp/19/19137.pdf",
    "media": {
      "iTunesURL": "itpc://webtv.bundestag.de/player/macros/bttv/podcast/video/auswahl.xml?contentIds=7408236",
      "mediathekURL": "https://dbtg.tv/fvid/7408236",
      "videoURLs": [
        {
          "URL": "https://cldf-od.r53.cdn.tv1.eu/1000153copo/ondemand/app144277506/145293313/7408236/7408236_h264_1920_1080_5000kb_baseline_de_5000.mp4?fdl=1",
          "description": "hoch (5000 kb)"
        },
        {
          "URL": "https://cldf-od.r53.cdn.tv1.eu/1000153copo/ondemand/app144277506/145293313/7408236/7408236_h264_720_400_2000kb_baseline_de_2192.mp4?fdl=1",
          "description": "mittel (2000 kb)"
        },
        {
          "URL": "https://cldf-od.r53.cdn.tv1.eu/1000153copo/ondemand/app144277506/145293313/7408236/7408236_h264_512_288_514kb_baseline_de_514.mp4?fdl=1",
          "description": "niedrig (514 kb)"
        },
        {
          "URL": "https://cldf-od.r53.cdn.tv1.eu/1000153copo/ondemand/app144277506/145293313/7408236/7408236_mp3_128kb_stereo_de_128.mp3?fdl=1",
          "description": "Audio (MP3)"
        }
      ]
    },
    "speeches": []
  }
}